tqdmnd/__init__.py
tqdmnd/tqdmnd.py
tqdmnd-1.0.0.dist-info/LICENSE
tqdmnd-1.0.0.dist-info/METADATA
tqdmnd-1.0.0.dist-info/WHEEL
tqdmnd-1.0.0.dist-info/top_level.txt
tqdmnd-1.0.0.dist-info/RECORD
