Metadata-Version: 2.1
Name: tqdmnd
Version: 1.0.0
Summary: A simple wrapper for tqdm supporting N-dimensional spaces
Author-email: Steven Zeltmann <steven.zeltmann@lbl.gov>
Project-URL: Homepage, https://github.com/sezelt/tqdmnd
Project-URL: Bug Tracker, https://github.com/sezelt/tqdmnd/issues
Classifier: Programming Language :: Python :: 3
Classifier: Operating System :: OS Independent
Requires-Python: >=3.10
License-File: LICENSE
Requires-Dist: tqdm
Requires-Dist: numpy
